Metadata-Version: 1.0
Name: NovokhatniyV-numerical-methods
Version: 0.0
Summary: numerical_methods_financial_University_first_second_third_seventh_eighth_tasks
Home-page: UNKNOWN
Author: UNKNOWN
Author-email: vova2002n@gmail.com
License: UNKNOWN
Platform: UNKNOWN
